text2structured_summary/__init__.py
text2structured_summary/main.py
text2structured_summary/prompts.py
text2structured_summary-2025.12.21183445.dist-info/METADATA
text2structured_summary-2025.12.21183445.dist-info/WHEEL
text2structured_summary-2025.12.21183445.dist-info/top_level.txt
text2structured_summary-2025.12.21183445.dist-info/RECORD
