Metadata-Version: 2.4
Name: text2structured-summary
Version: 2025.12.21183445
Summary: text2structured-summary generates structured summaries from unstructured text using an LLM.
Author-email: text2structured-summary <hi@eugene.plus>
License: MIT
Project-URL: Homepage, https://github.com/chigwell/text2structured-summary
Requires-Python: >=3.9
Requires-Dist: langchain-llm7>=0.0.0
Requires-Dist: llmatch-messages>=0.0.0
Requires-Dist: langchain-core>=0.3.0
